{
    "AX": {
        "error": 0.0048614597046010965, 
        "filter_outliers_dict": {
            "filter_outliers": true, 
            "iterations": 1, 
            "std_devs": 2
        }, 
        "fit": "average", 
        "value": 0.04567592263157862
    }, 
    "CDD": {
        "error": 3.2883566364232903e-06, 
        "filter_outliers_dict": {
            "filter_outliers": true, 
            "iterations": 1, 
            "std_devs": 10
        }, 
        "fit": "average", 
        "value": 7.506192697621149e-06
    }, 
    "H1": {
        "error": 0.004146301255847773, 
        "filter_outliers_dict": {
            "filter_outliers": true, 
            "iterations": 1, 
            "std_devs": 2
        }, 
        "fit": "average", 
        "value": -0.043589273587902266
    }, 
    "H2": {
        "error": 0.005214244558448171, 
        "filter_outliers_dict": {
            "filter_outliers": true, 
            "iterations": 1, 
            "std_devs": 2
        }, 
        "fit": "average", 
        "value": 0.0708427520096739
    }, 
    "L1": {
        "error": 0.0016370314173349998, 
        "filter_outliers_dict": {
            "filter_outliers": true, 
            "iterations": 1, 
            "std_devs": 2
        }, 
        "fit": "average", 
        "value": -0.001272393742018279
    }, 
    "L2": {
        "error": 0.0034235836828368123, 
        "filter_outliers_dict": {
            "filter_outliers": true, 
            "iterations": 1, 
            "std_devs": 2
        }, 
        "fit": "average", 
        "value": 0.14540818331413044
    }
}